pq/__init__.py
pq/__main__.py
pq/cli.py
pq/pq.py
pq/utils.py
pq_json-0.0.3.1.dist-info/LICENSE
pq_json-0.0.3.1.dist-info/METADATA
pq_json-0.0.3.1.dist-info/WHEEL
pq_json-0.0.3.1.dist-info/entry_points.txt
pq_json-0.0.3.1.dist-info/top_level.txt
pq_json-0.0.3.1.dist-info/RECORD
