Metadata-Version: 2.1
Name: pq-json
Version: 0.0.3.1
Summary: pq is a Python command-line JSON processor
Home-page: https://github.com/mumubebe/pq/
Author: mumubebe
License: UNKNOWN
Project-URL: Bug Tracker, https://github.com/mumubebe/pq/issues
Platform: UNKNOWN
Classifier: Programming Language :: Python :: 3
Classifier: License :: OSI Approved :: MIT License
Classifier: Development Status :: 3 - Alpha
Requires-Python: >=3.6
License-File: LICENSE
Requires-Dist: rich
